{
  "characters": [
    {
      "id": "excavator",
      "name": "The Excavator",
      "description": "A veteran miner who strikes hard and can take a beating. Balanced offense and defense.",
      "maxHp": 80,
      "startingGold": 99,
      "startingDeck": [
        "delve",
        "delve",
        "delve",
        "delve",
        "delve",
        "brace",
        "brace",
        "brace",
        "brace",
        "brace",
        "sunder"
      ],
      "startingRelic": "miners_resolve"
    },
    {
      "id": "scout",
      "name": "The Scout",
      "description": "A swift explorer who relies on agility and card draw to outmaneuver foes.",
      "maxHp": 70,
      "startingGold": 99,
      "startingDeck": [
        "delve",
        "delve",
        "delve",
        "delve",
        "delve",
        "brace",
        "brace",
        "brace",
        "brace",
        "tunnel_vision",
        "pickaxe_swing"
      ],
      "startingRelic": "serpent_ring"
    },
    {
      "id": "bulwark",
      "name": "The Bulwark",
      "description": "A stalwart defender with high HP who specializes in outlasting enemies.",
      "maxHp": 95,
      "startingGold": 99,
      "startingDeck": [
        "delve",
        "delve",
        "delve",
        "delve",
        "brace",
        "brace",
        "brace",
        "brace",
        "brace",
        "brace",
        "lantern_bash",
        "gear_up"
      ],
      "startingRelic": "iron_anchor"
    }
  ]
}
